colordebug.py
colordebug-1.0.0.dist-info/licenses/LICENSE.md
colordebug-1.0.0.dist-info/METADATA
colordebug-1.0.0.dist-info/WHEEL
colordebug-1.0.0.dist-info/top_level.txt
colordebug-1.0.0.dist-info/RECORD
