Metadata-Version: 2.4
Name: colordebug
Version: 1.0.0
Summary: Colorful debugging utilities for Python with text wrapping, async support, and security features
Author-email: garantiatsverga <hmurovicdanila@gmail.com>
License:                                  Apache License
Project-URL: Homepage, https://github.com/garantiatsverga/colordebug
Project-URL: Repository, https://github.com/garantiatsverga/colordebug
Project-URL: Issues, https://github.com/garantiatsverga/colordebug/issues
Keywords: debugging,logging,color,async,security,text-wrapping
Classifier: Development Status :: 5 - Production/Stable
Classifier: Intended Audience :: Developers
Classifier: Topic :: Software Development :: Debuggers
Classifier: Topic :: System :: Logging
Classifier: License :: OSI Approved :: Apache Software License
Classifier: Programming Language :: Python :: 3
Classifier: Programming Language :: Python :: 3.8
Classifier: Programming Language :: Python :: 3.9
Classifier: Programming Language :: Python :: 3.10
Classifier: Programming Language :: Python :: 3.11
Classifier: Programming Language :: Python :: 3.12
Classifier: Operating System :: OS Independent
Classifier: Framework :: AsyncIO
Classifier: Framework :: FastAPI
Classifier: Framework :: Flask
Requires-Python: >=3.8
License-File: LICENSE.md
Dynamic: license-file
